README.md
setup.py
pc23/__init__.py
pc23.egg-info/PKG-INFO
pc23.egg-info/SOURCES.txt
pc23.egg-info/dependency_links.txt
pc23.egg-info/not-zip-safe
pc23.egg-info/top_level.txt