Metadata-Version: 1.1
Name: pc23
Version: 1.1.0
Summary: PC23 Python 2.x - 3.x compatibility library
Home-page: https://bitbucket.org/deniskhodus/pc23
Author: Denis Khodus
Author-email: deniskhodus@gmail.com
License: MIT
Keywords: pc23 compatibility
Platform: UNKNOWN
Classifier: Development Status :: 5 - Production/Stable
Classifier: License :: OSI Approved :: Mozilla Public License 2.0 (MPL 2.0)
Classifier: Programming Language :: Python :: 2
Classifier: Programming Language :: Python :: 3
Classifier: Topic :: Software Development
Classifier: Topic :: Software Development :: Libraries
Classifier: Topic :: Software Development :: Libraries :: Python Modules
